metatensor/torch/__init__.py
metatensor/torch/_build_versions.py
metatensor/torch/_c_lib.py
metatensor/torch/_module.py
metatensor/torch/documentation.py
metatensor/torch/learn.py
metatensor/torch/operations.py
metatensor/torch/serialization.py
metatensor/torch/utils.py
metatensor/torch/version.py
metatensor/torch/atomistic/__init__.py
metatensor/torch/atomistic/ase_calculator.py
metatensor/torch/atomistic/io.py
metatensor/torch/torch-2.1/include/metatensor/torch.hpp
metatensor/torch/torch-2.1/include/metatensor/torch/array.hpp
metatensor/torch/torch-2.1/include/metatensor/torch/block.hpp
metatensor/torch/torch-2.1/include/metatensor/torch/exports.h
metatensor/torch/torch-2.1/include/metatensor/torch/labels.hpp
metatensor/torch/torch-2.1/include/metatensor/torch/misc.hpp
metatensor/torch/torch-2.1/include/metatensor/torch/module.hpp
metatensor/torch/torch-2.1/include/metatensor/torch/tensor.hpp
metatensor/torch/torch-2.1/include/metatensor/torch/version.h
metatensor/torch/torch-2.1/lib/libmetatensor_torch.dylib
metatensor/torch/torch-2.1/lib/cmake/metatensor_torch/metatensor_torch-config-version.cmake
metatensor/torch/torch-2.1/lib/cmake/metatensor_torch/metatensor_torch-config.cmake
metatensor/torch/torch-2.1/lib/cmake/metatensor_torch/metatensor_torch-targets-release.cmake
metatensor/torch/torch-2.1/lib/cmake/metatensor_torch/metatensor_torch-targets.cmake
metatensor/torch/torch-2.2/include/metatensor/torch.hpp
metatensor/torch/torch-2.2/include/metatensor/torch/array.hpp
metatensor/torch/torch-2.2/include/metatensor/torch/block.hpp
metatensor/torch/torch-2.2/include/metatensor/torch/exports.h
metatensor/torch/torch-2.2/include/metatensor/torch/labels.hpp
metatensor/torch/torch-2.2/include/metatensor/torch/misc.hpp
metatensor/torch/torch-2.2/include/metatensor/torch/module.hpp
metatensor/torch/torch-2.2/include/metatensor/torch/tensor.hpp
metatensor/torch/torch-2.2/include/metatensor/torch/version.h
metatensor/torch/torch-2.2/lib/libmetatensor_torch.dylib
metatensor_torch-0.8.2.dist-info/licenses/AUTHORS
metatensor_torch-0.8.2.dist-info/licenses/LICENSE
metatensor_torch-0.8.2.dist-info/METADATA
metatensor_torch-0.8.2.dist-info/WHEEL
metatensor_torch-0.8.2.dist-info/top_level.txt
metatensor_torch-0.8.2.dist-info/RECORD
