Metadata-Version: 2.4
Name: metatensor-torch
Version: 0.8.2
Summary: TorchScript bindings for metatensor
Author: Guillaume Fraux, Philip Loche, Filippo Bigi, Joseph W. Abbott, Davide Tisi, Alexander Goscinski, Michele Ceriotti
License-Expression: BSD-3-Clause
Project-URL: homepage, https://docs.metatensor.org/latest/
Project-URL: documentation, https://docs.metatensor.org/latest/
Project-URL: repository, https://github.com/metatensor/metatensor
Project-URL: changelog, https://docs.metatensor.org/latest/torch/CHANGELOG.html
Keywords: machine learning,molecular modeling,torch
Classifier: Development Status :: 4 - Beta
Classifier: Intended Audience :: Science/Research
Classifier: Operating System :: POSIX
Classifier: Operating System :: MacOS :: MacOS X
Classifier: Operating System :: Microsoft :: Windows
Classifier: Programming Language :: Python
Classifier: Programming Language :: Python :: 3
Classifier: Topic :: Scientific/Engineering
Classifier: Topic :: Scientific/Engineering :: Bio-Informatics
Classifier: Topic :: Scientific/Engineering :: Chemistry
Classifier: Topic :: Scientific/Engineering :: Physics
Classifier: Topic :: Software Development :: Libraries
Classifier: Topic :: Software Development :: Libraries :: Python Modules
Requires-Python: >=3.10
License-File: LICENSE
License-File: AUTHORS
Requires-Dist: torch >=2.1,<2.3
Requires-Dist: metatensor-core<0.2,>=0.1.15
Dynamic: author
Dynamic: license-file
Dynamic: requires-dist
